fastapi_amis_admin_nav/__init__.py
fastapi_amis_admin_nav/admin.py
fastapi_amis_admin_nav/models.py
fastapi_amis_admin_nav/utils.py
fastapi_amis_admin_nav-0.1.4.dist-info/WHEEL
fastapi_amis_admin_nav-0.1.4.dist-info/METADATA
fastapi_amis_admin_nav-0.1.4.dist-info/RECORD
