Metadata-Version: 2.1
Name: fastapi_amis_admin_nav
Version: 0.1.4
Summary: FastAPI-Amis-Admin-Nav是一个基于FastAPI-Amis-Admin并且为FastAPI-Amis-Admin提供可视化导航页面管理的拓展库.
Keywords: fastapi,fastapi-user-auth,fastapi-amis-admin,fastapi-amis-admin-nav
Author-email: Atomi <1456417373@qq.com>
Maintainer-email: Atomi <1456417373@qq.com>
Requires-Python: >=3.7
Classifier: Framework :: FastAPI
Classifier: Environment :: Web Environment
Classifier: Topic :: System :: Systems Administration
Classifier: License :: OSI Approved :: Apache Software License
Classifier: Operating System :: OS Independent
Classifier: Programming Language :: Python :: 3
Classifier: Programming Language :: Python :: 3.7
Classifier: Programming Language :: Python :: 3.8
Classifier: Programming Language :: Python :: 3.9
Classifier: Programming Language :: Python :: 3.10
Requires-Dist: fastapi-amis-admin>=0.7.0a2
Project-URL: Documentation, http://docs.amis.work/
Project-URL: FastAPI-Amis-Admin, https://github.com/amisadmin/fastapi_amis_admin
Project-URL: Source, https://github.com/amisadmin/fastapi_amis_admin_nav
